{"v":"5.1.12","fr":50,"ip":0,"op":200,"w":174,"h":125,"nm":"负反馈长按引导2","ddd":0,"assets":[{"id":"comp_0","layers":[{"ddd":0,"ind":1,"ty":4,"nm":"形状","sr":1,"ks":{"o":{"a":1,"k":[{"i":{"x":[0.833],"y":[0.833]},"o":{"x":[0.167],"y":[0.167]},"n":["0p833_0p833_0p167_0p167"],"t":0,"s":[0],"e":[100]},{"t":25}],"ix":11},"r":{"a":0,"k":0,"ix":10},"p":{"a":0,"k":[173.997,195.116,0],"ix":2},"a":{"a":0,"k":[0,0,0],"ix":1},"s":{"a":0,"k":[66.667,66.667,100],"ix":6}},"ao":0,"shapes":[{"ty":"gr","it":[{"ind":0,"ty":"sh","ix":1,"ks":{"a":0,"k":{"i":[[0,0],[0,0],[-0.48,1.03],[0,0],[0,0],[0,0],[0,0],[0,0],[6.05,-3.42],[0,0],[-2.55,2.85],[0,0]],"o":[[0,0],[0.59,-0.98],[0,0],[0,0],[0,0],[0,0],[0,0],[-2.47,4.81],[0,0],[3.81,-2.29],[0,0],[0,0]],"v":[[-35.516,-6.912],[-35.516,-25.782],[-33.916,-28.802],[-24.926,-28.802],[-24.926,-31.662],[-49.116,-31.662],[-49.116,-28.802],[-37.246,-28.802],[-50.016,-16.482],[-48.086,-13.942],[-38.536,-21.662],[-38.536,-6.912]],"c":true},"ix":2},"nm":"路径 1","mn":"ADBE Vector Shape - Group","hd":false},{"ind":1,"ty":"sh","ix":2,"ks":{"a":0,"k":{"i":[[-1.79,-2.35],[0,0],[3.11,2.44],[0,0]],"o":[[0,0],[-2.13,-2.44],[0,0],[3.3,2.71]],"v":[[-26.414,-14.36],[-24.114,-16.68],[-31.984,-23.99],[-34.084,-21.97]],"c":true},"ix":2},"nm":"路径 2","mn":"ADBE Vector Shape - Group","hd":false},{"ind":2,"ty":"sh","ix":3,"ks":{"a":0,"k":{"i":[[0,0],[0,0],[0,0],[0,0],[0,0],[0,0],[0,0],[0,0],[0,0],[0,0],[0,0],[0,0],[0,0],[0,0],[0,0],[0,0]],"o":[[0,0],[0,0],[0,0],[0,0],[0,0],[0,0],[0,0],[0,0],[0,0],[0,0],[0,0],[0,0],[0,0],[0,0],[0,0],[0,0]],"v":[[2.146,-25.614],[2.146,-27.914],[-7.094,-27.914],[-7.094,-29.034],[2.986,-29.034],[2.986,-31.384],[-7.094,-31.384],[-7.094,-32.894],[-9.954,-32.894],[-9.954,-31.384],[-20.004,-31.384],[-20.004,-29.034],[-9.954,-29.034],[-9.954,-27.914],[-19.194,-27.914],[-19.194,-25.614]],"c":true},"ix":2},"nm":"路径 3","mn":"ADBE Vector Shape - Group","hd":false},{"ind":3,"ty":"sh","ix":4,"ks":{"a":0,"k":{"i":[[0,0],[0,0],[0,0],[0,0],[0,0],[0,0],[0,0],[0,0],[0,0],[0,0],[0,0],[0,0]],"o":[[0,0],[0,0],[0,0],[0,0],[0,0],[0,0],[0,0],[0,0],[0,0],[0,0],[0,0],[0,0]],"v":[[4.076,-15.284],[4.076,-17.694],[-2.504,-17.694],[-1.694,-19.114],[0.496,-19.114],[0.496,-24.634],[-17.564,-24.634],[-17.564,-19.114],[-14.934,-19.114],[-14.324,-17.694],[-21.124,-17.694],[-21.124,-15.284]],"c":true},"ix":2},"nm":"路径 4","mn":"ADBE Vector Shape - Group","hd":false},{"ind":4,"ty":"sh","ix":5,"ks":{"a":0,"k":{"i":[[0,0],[0,0],[0,0],[0,0]],"o":[[0,0],[0,0],[0,0],[0,0]],"v":[[-2.276,-21.194],[-14.796,-21.194],[-14.796,-22.534],[-2.276,-22.534]],"c":true},"ix":2},"nm":"路径 5","mn":"ADBE Vector Shape - Group","hd":false},{"ind":5,"ty":"sh","ix":6,"ks":{"a":0,"k":{"i":[[0,0],[0,0],[0,0],[0,0]],"o":[[0,0],[0,0],[0,0],[0,0]],"v":[[-5.586,-17.688],[-11.236,-17.688],[-11.856,-19.118],[-4.796,-19.118]],"c":true},"ix":2},"nm":"路径 6","mn":"ADBE Vector Shape - Group","hd":false},{"ind":6,"ty":"sh","ix":7,"ks":{"a":0,"k":{"i":[[0,0],[0,0],[0,0],[0,0],[0,0],[0,0],[0,0],[0,0]],"o":[[0,0],[0,0],[0,0],[0,0],[0,0],[0,0],[0,0],[0,0]],"v":[[-15.16,-6.91],[-15.16,-7.92],[-1.86,-7.92],[-1.86,-6.91],[0.94,-6.91],[0.94,-14.19],[-17.96,-14.19],[-17.96,-6.91]],"c":true},"ix":2},"nm":"路径 7","mn":"ADBE Vector Shape - Group","hd":false},{"ind":7,"ty":"sh","ix":8,"ks":{"a":0,"k":{"i":[[0,0],[0,0],[0,0],[0,0]],"o":[[0,0],[0,0],[0,0],[0,0]],"v":[[-1.86,-10.27],[-15.16,-10.27],[-15.16,-11.81],[-1.86,-11.81]],"c":true},"ix":2},"nm":"路径 8","mn":"ADBE Vector Shape - Group","hd":false},{"ind":8,"ty":"sh","ix":9,"ks":{"a":0,"k":{"i":[[0,0],[-0.44,2.38],[0,0],[0,0],[-0.2,1.4],[0,0],[1.79,-2.52],[0,0],[-0.7,2.08],[0,0],[0.56,-1.54]],"o":[[0.67,-2.35],[0,0],[0,0],[0.28,-1.21],[0,0],[-0.5,4.54],[0,0],[1.01,-1.28],[0,0],[-0.39,2.08],[0,0]],"v":[[30.53,-19.818],[32.18,-26.928],[32.18,-28.858],[23.34,-28.858],[24.04,-32.778],[21.12,-33.258],[17.68,-22.648],[20.03,-20.998],[22.58,-26.038],[29.1,-26.038],[27.68,-20.628]],"c":true},"ix":2},"nm":"路径 9","mn":"ADBE Vector Shape - Group","hd":false},{"ind":9,"ty":"sh","ix":10,"ks":{"a":0,"k":{"i":[[0,0],[-1.57,3.02],[-0.84,-1.29],[0,0],[0,0],[0,0],[0,0],[0.45,0.62],[-0.62,3.41],[0,0],[0,0],[0,0],[0,0],[0.62,-2.02],[1.26,1.26],[0,0],[-1.57,-2.05],[2.21,-1.62]],"o":[[2.21,-1.79],[0.87,1.23],[0,0],[0,0],[0,0],[0,0],[-0.47,-0.65],[1,-2.68],[0,0],[0,0],[0,0],[0,0],[-0.39,2.38],[-1.51,-1.91],[0,0],[1.73,1.96],[-1.38,3.02],[0,0]],"v":[[8.388,-7.864],[14.038,-15.084],[16.588,-11.304],[18.718,-13.464],[17.728,-14.864],[17.728,-14.864],[16.768,-16.214],[15.388,-18.114],[17.848,-27.264],[17.848,-29.954],[7.428,-29.954],[7.428,-27.124],[14.988,-27.124],[13.478,-20.544],[9.308,-25.304],[7.378,-23.454],[12.308,-17.464],[6.928,-10.494]],"c":true},"ix":2},"nm":"路径 10","mn":"ADBE Vector Shape - Group","hd":false},{"ind":10,"ty":"sh","ix":11,"ks":{"a":0,"k":{"i":[[-2.52,-2.21],[0,0],[1.35,4.14],[0,1.93],[0,0],[0.73,-2.24],[3.08,-1.85],[0,0],[-1.01,3.22]],"o":[[0,0],[-3.24,-2.49],[0.23,-1.62],[0,0],[-0.03,3.53],[-0.95,2.61],[0,0],[3.61,-2.1],[1.4,3.11]],"v":[[31.144,-6.914],[33.104,-9.204],[26.244,-19.174],[26.584,-24.494],[23.704,-24.494],[22.554,-15.844],[16.504,-9.174],[18.354,-6.914],[25.294,-14.894]],"c":true},"ix":2},"nm":"路径 11","mn":"ADBE Vector Shape - Group","hd":false},{"ind":11,"ty":"sh","ix":12,"ks":{"a":0,"k":{"i":[[0,0],[0,0],[-0.28,0.56],[-0.5,0.39],[0,0],[0,0],[0,0],[0,0],[0,0],[0,0],[0,0],[0,0],[0,0],[-0.02,0.02],[0,1.4],[1.12,0.98],[1.82,0],[1.2,-1.17],[0,-2.08],[0,0],[-0.47,0.65],[-1.2,0],[-0.53,-0.53],[0,-0.92],[0.51,-0.62],[0,0],[0,0],[0,0],[0,0],[0,0],[0,0],[0.25,-0.53],[0,-1.06],[0,0]],"o":[[0,0],[0,-0.67],[0.25,-0.5],[0,0],[0,0],[0,0],[0,0],[0,0],[0,0],[0,0],[0,0],[0,0],[0.02,-0.02],[0.67,-0.9],[0,-1.71],[-1.12,-1],[-2.07,0],[-1.23,1.18],[0,0],[0,-1.21],[0.56,-0.75],[0.96,0],[0.51,0.53],[0,0.7],[0,0],[0,0],[0,0],[0,0],[0,0],[0,0],[-0.96,0.95],[-0.39,0.75],[0,0],[0,0]],"v":[[43.716,-15.482],[43.716,-15.872],[44.136,-17.722],[45.256,-19.092],[45.886,-19.642],[45.886,-19.642],[46.426,-20.122],[46.426,-20.122],[47.116,-20.762],[47.116,-20.762],[47.496,-21.122],[47.496,-21.122],[47.616,-21.252],[47.666,-21.302],[48.696,-24.742],[47.016,-28.782],[42.596,-30.262],[37.696,-28.502],[35.876,-23.622],[39.066,-23.622],[39.766,-26.402],[42.396,-27.522],[44.636,-26.732],[45.426,-24.552],[44.666,-22.562],[44.336,-22.172],[43.806,-21.692],[43.806,-21.692],[43.326,-21.252],[43.326,-21.252],[42.886,-20.832],[41.056,-18.612],[40.496,-15.872],[40.496,-15.482]],"c":true},"ix":2},"nm":"路径 12","mn":"ADBE Vector Shape - Group","hd":false},{"ind":12,"ty":"sh","ix":13,"ks":{"a":0,"k":{"i":[[-0.62,0],[-0.44,0.39],[0,0.62],[0.4,0.39],[0.61,0],[0.37,-0.31],[0,0],[0,-0.62],[-0.36,-0.37],[0,0]],"o":[[0.61,0],[0.4,-0.39],[0,-0.62],[-0.42,-0.39],[-0.55,0],[0,0],[-0.44,0.39],[0,0.55],[0,0],[0.4,0.39]],"v":[[42.096,-9.876],[43.656,-10.466],[44.276,-12.006],[43.656,-13.516],[42.096,-14.106],[40.716,-13.646],[40.576,-13.516],[39.936,-12.006],[40.456,-10.616],[40.576,-10.496]],"c":true},"ix":2},"nm":"路径 13","mn":"ADBE Vector Shape - Group","hd":false},{"ind":13,"ty":"sh","ix":14,"ks":{"a":0,"k":{"i":[[0,0],[-2.85,0.95],[0,0],[1.87,-0.48],[0,0],[0,0],[-5.66,-3],[0,0],[1.18,3.95],[0,0],[0,0],[0,0],[0,0],[0,0],[0,0],[0,0],[0,0],[0,0],[0,0],[0.5,-0.26]],"o":[[3.25,-0.72],[0,0],[-1.85,0.64],[0,0],[0,0],[1.18,5.07],[0,0],[-4.95,-2.27],[0,0],[0,0],[0,0],[0,0],[0,0],[0,0],[0,0],[0,0],[0,0],[0,0],[0,0.61],[0,0]],"v":[[-78.576,32.946],[-69.446,30.456],[-70.196,27.716],[-75.796,29.396],[-75.796,20.516],[-70.846,20.516],[-60.566,32.616],[-58.836,29.846],[-68.016,20.516],[-59.226,20.516],[-59.226,17.666],[-75.796,17.666],[-75.796,7.246],[-78.736,7.246],[-78.736,17.666],[-84.116,17.666],[-84.116,20.516],[-78.736,20.516],[-78.736,28.976],[-79.496,30.266]],"c":true},"ix":2},"nm":"路径 14","mn":"ADBE Vector Shape - Group","hd":false},{"ind":14,"ty":"sh","ix":15,"ks":{"a":0,"k":{"i":[[0,0],[-2.24,2.52],[0,0],[4.4,-1.9]],"o":[[4.45,-1.99],[0,0],[-2.13,2.38],[0,0]],"v":[[-72.016,16.126],[-61.996,9.376],[-63.956,7.386],[-73.756,13.796]],"c":true},"ix":2},"nm":"路径 15","mn":"ADBE Vector Shape - Group","hd":false},{"ind":15,"ty":"sh","ix":16,"ks":{"a":0,"k":{"i":[[0,0],[0,0],[0,0],[0,0],[0,0],[0,0],[0,0],[0.34,0.95],[0,0],[-0.31,-0.98],[0,0],[0,0]],"o":[[0,0],[0,0],[0,0],[0,0],[0,0],[0,0],[-0.34,-1.17],[0,0],[0.39,0.82],[0,0],[0,0],[0,0]],"v":[[-43.634,16.066],[-43.634,12.676],[-33.884,12.676],[-33.884,15.956],[-31.084,15.956],[-31.084,10.016],[-37.444,10.016],[-38.454,6.826],[-41.444,7.326],[-40.384,10.016],[-46.404,10.016],[-46.404,16.066]],"c":true},"ix":2},"nm":"路径 16","mn":"ADBE Vector Shape - Group","hd":false},{"ind":16,"ty":"sh","ix":17,"ks":{"a":0,"k":{"i":[[0,0],[0,1.9],[0,0],[-0.73,0.36],[0,0],[0.73,-0.34],[0,0],[0,0],[0,0],[0,0],[0,0],[0,0],[0,0],[0,0],[0,0],[0,0],[0,0],[1.2,-0.28],[0,0],[0,0],[0,0],[0,0],[0,0],[0,0],[0.56,0],[0.7,0.11],[0,0]],"o":[[1.87,0],[0,0],[0.73,-0.33],[0,0],[-0.73,0.39],[0,0],[0,0],[0,0],[0,0],[0,0],[0,0],[0,0],[0,0],[0,0],[0,0],[0,0],[-1.18,0.4],[0,0],[0,0],[0,0],[0,0],[0,0],[0,0],[0,0.62],[-0.65,0],[0,0],[0,0]],"v":[[-52.728,32.778],[-49.908,29.928],[-49.908,22.308],[-47.688,21.248],[-47.688,18.278],[-49.908,19.398],[-49.908,14.998],[-47.578,14.998],[-47.578,12.178],[-49.908,12.178],[-49.908,7.218],[-52.868,7.218],[-52.868,12.178],[-55.838,12.178],[-55.838,14.998],[-52.868,14.998],[-52.868,20.598],[-56.428,21.578],[-55.668,24.518],[-54.748,24.208],[-54.748,24.208],[-52.868,23.538],[-52.868,23.538],[-52.868,29.168],[-53.738,30.118],[-55.758,29.958],[-55.108,32.778]],"c":true},"ix":2},"nm":"路径 17","mn":"ADBE Vector Shape - Group","hd":false},{"ind":17,"ty":"sh","ix":18,"ks":{"a":0,"k":{"i":[[0,0],[-2.02,1.62],[0,0],[0,0],[0,0],[0,0],[0,0],[-0.95,-0.69],[0,0],[2.41,1.28],[-0.45,2.52],[0,0],[0,0],[0,0],[0,0],[-0.22,0.93],[0,0],[0.42,-1.34],[0,0],[0,0],[0,0],[0.67,-1.35],[-1.04,-0.58],[0,0],[0,0],[3.14,-0.7]],"o":[[4.03,-0.98],[0,0],[0,0],[0,0],[0,0],[0,0],[1.24,0.8],[0,0],[-1.51,-1.06],[1.29,-1.77],[0,0],[0,0],[0,0],[0,0],[0.23,-0.83],[0,0],[-0.34,1.4],[0,0],[0,0],[0,0],[-0.56,1.45],[1.12,0.59],[0,0],[0,0],[-1.82,1.15],[0,0]],"v":[[-46.988,33.256],[-37.918,29.366],[-37.398,29.686],[-37.398,29.686],[-36.388,30.316],[-36.388,30.316],[-35.438,30.916],[-32.148,33.146],[-30.168,30.846],[-36.018,27.326],[-33.408,20.886],[-30.328,20.886],[-30.328,18.106],[-39.688,18.106],[-39.338,16.896],[-38.648,14.246],[-41.528,13.966],[-42.648,18.106],[-46.938,18.106],[-46.938,20.886],[-43.628,20.886],[-45.508,25.086],[-42.268,26.856],[-40.748,27.716],[-40.748,27.716],[-48.168,30.486]],"c":true},"ix":2},"nm":"路径 18","mn":"ADBE Vector Shape - Group","hd":false},{"ind":18,"ty":"sh","ix":19,"ks":{"a":0,"k":{"i":[[1.15,-1.34],[0.58,0.3],[0,0],[0.21,0.1],[-0.48,1.23],[0,0]],"o":[[-0.53,-0.29],[0,0],[-0.2,-0.1],[0.5,-0.93],[0,0],[-0.45,2.02]],"v":[[-38.622,25.922],[-40.292,25.032],[-41.482,24.432],[-42.092,24.132],[-40.632,20.882],[-36.212,20.882]],"c":true},"ix":2},"nm":"路径 19","mn":"ADBE Vector Shape - Group","hd":false},{"ind":19,"ty":"sh","ix":20,"ks":{"a":0,"k":{"i":[[0,0],[-2.16,2.38],[-1.4,-1.68],[0,0],[2.02,1.74],[-0.78,2.89],[0,0],[0,0],[0,0],[0,0],[0,0],[0,0],[0.18,0.56],[0,0],[-0.34,-1.21],[0,0],[0,0],[0,0],[1.06,-1.63],[1.98,1.45],[0,0],[-1.79,-1.54],[3,-0.93]],"o":[[3.14,-1.1],[1.9,1.76],[0,0],[-1.65,-1.73],[1.34,-2.07],[0,0],[0,0],[0,0],[0,0],[0,0],[0,0],[-0.18,-0.64],[0,0],[0.39,1.01],[0,0],[0,0],[0,0],[-0.62,2.08],[-1.74,-1.46],[0,0],[2.13,1.57],[-1.96,2.05],[0,0]],"v":[[-17.71,28.698],[-9.78,23.488],[-4.83,28.668],[-2.53,26.368],[-8.02,21.158],[-4.8,13.738],[-2.56,13.738],[-2.56,10.918],[-9.34,10.918],[-9.61,9.868],[-9.61,9.868],[-9.88,8.878],[-10.43,7.078],[-13.42,7.578],[-12.33,10.918],[-18.83,10.918],[-18.83,13.738],[-7.71,13.738],[-10.2,19.318],[-15.8,14.978],[-17.79,16.908],[-11.94,21.578],[-19.36,26.038]],"c":true},"ix":2},"nm":"路径 20","mn":"ADBE Vector Shape - Group","hd":false},{"ind":20,"ty":"sh","ix":21,"ks":{"a":0,"k":{"i":[[-1.06,-1.4],[0,0],[1.84,1.46],[0,0]],"o":[[0,0],[-1.29,-1.46],[0,0],[2.02,1.63]],"v":[[-22.188,13.798],[-20.088,11.728],[-24.788,7.358],[-26.808,9.258]],"c":true},"ix":2},"nm":"路径 21","mn":"ADBE Vector Shape - Group","hd":false},{"ind":21,"ty":"sh","ix":22,"ks":{"a":0,"k":{"i":[[1.4,-2.24],[0,0],[0,0],[0,0],[0,0],[0,0],[0,0],[0,0],[0,0],[0,0],[0,0],[-0.33,0],[-0.37,-0.48],[-1.12,-0.33],[-1.79,-0.03],[0,0],[0,0],[0,0],[-0.21,0],[0,0],[0,0],[0,0],[0,0],[0,0],[0,0],[0,0],[0,0],[0,0],[0,0],[0,0],[0.35,0],[0,0],[0,0],[0,0],[0,0],[0,0],[0,0],[0.81,0.42],[0.61,0.73],[0,0],[0,0],[0,0],[0,0],[0,0],[0,0]],"o":[[0,0],[0,0],[0,0],[0,0],[0,0],[0,0],[0,0],[0,0],[0,0],[0,0],[0.67,-1],[0.34,0],[0.81,0.95],[1.18,0.28],[0,0],[0,0],[0,0],[0.22,0],[0,0],[0,0],[0,0],[0,0],[0,0],[0,0],[0,0],[0,0],[0,0],[0,0],[0,0],[-0.35,0],[0,0],[0,0],[0,0],[0,0],[0,0],[0,0],[-1.62,-0.06],[-0.64,-0.36],[0,0],[0,0],[0,0],[0,0],[0,0],[0,0],[-1.12,0.62]],"v":[[-27.172,31.182],[-25.012,33.202],[-24.712,32.662],[-24.712,32.662],[-24.422,32.162],[-24.422,32.162],[-24.152,31.712],[-24.152,31.712],[-23.892,31.292],[-23.892,31.292],[-23.642,30.922],[-22.132,29.422],[-21.092,30.122],[-18.212,32.052],[-13.792,32.532],[-10.882,32.572],[-10.882,32.572],[-9.512,32.582],[-8.862,32.582],[-2.452,32.582],[-1.752,29.702],[-2.382,29.742],[-2.382,29.742],[-3.412,29.802],[-3.412,29.802],[-5.022,29.872],[-5.022,29.872],[-6.102,29.872],[-6.102,29.872],[-8.232,29.892],[-9.282,29.902],[-11.122,29.892],[-11.122,29.892],[-13.372,29.862],[-13.372,29.862],[-14.882,29.842],[-14.882,29.842],[-18.522,29.142],[-20.422,27.492],[-20.702,27.212],[-20.702,16.542],[-27.112,16.542],[-27.112,19.232],[-23.422,19.232],[-23.422,26.902]],"c":true},"ix":2},"nm":"路径 22","mn":"ADBE Vector Shape - Group","hd":false},{"ind":22,"ty":"sh","ix":23,"ks":{"a":0,"k":{"i":[[0,0],[0,0],[0,0],[0,0],[0,0],[0,0],[0,0],[0,0],[0,0],[0,0],[0,0],[0,0],[0,0],[0,0],[0,0],[0,0],[0,0],[0,0],[0,0],[0,0]],"o":[[0,0],[0,0],[0,0],[0,0],[0,0],[0,0],[0,0],[0,0],[0,0],[0,0],[0,0],[0,0],[0,0],[0,0],[0,0],[0,0],[0,0],[0,0],[0,0],[0,0]],"v":[[26.218,32.276],[26.218,29.446],[15.268,29.446],[15.268,26.906],[25.048,26.906],[25.048,24.126],[15.268,24.126],[15.268,21.636],[23.928,21.636],[23.928,7.946],[3.598,7.946],[3.598,21.636],[12.308,21.636],[12.308,24.126],[2.528,24.126],[2.528,26.906],[12.308,26.906],[12.308,29.446],[1.328,29.446],[1.328,32.276]],"c":true},"ix":2},"nm":"路径 23","mn":"ADBE Vector Shape - Group","hd":false},{"ind":23,"ty":"sh","ix":24,"ks":{"a":0,"k":{"i":[[0,0],[0,0],[0,0],[0,0]],"o":[[0,0],[0,0],[0,0],[0,0]],"v":[[21.042,13.494],[15.272,13.494],[15.272,10.634],[21.042,10.634]],"c":true},"ix":2},"nm":"路径 24","mn":"ADBE Vector Shape - Group","hd":false},{"ind":24,"ty":"sh","ix":25,"ks":{"a":0,"k":{"i":[[0,0],[0,0],[0,0],[0,0]],"o":[[0,0],[0,0],[0,0],[0,0]],"v":[[12.3,13.494],[6.48,13.494],[6.48,10.634],[12.3,10.634]],"c":true},"ix":2},"nm":"路径 25","mn":"ADBE Vector Shape - Group","hd":false},{"ind":25,"ty":"sh","ix":26,"ks":{"a":0,"k":{"i":[[0,0],[0,0],[0,0],[0,0]],"o":[[0,0],[0,0],[0,0],[0,0]],"v":[[12.3,18.948],[6.48,18.948],[6.48,16.178],[12.3,16.178]],"c":true},"ix":2},"nm":"路径 26","mn":"ADBE Vector Shape - Group","hd":false},{"ind":26,"ty":"sh","ix":27,"ks":{"a":0,"k":{"i":[[0,0],[0,0],[0,0],[0,0]],"o":[[0,0],[0,0],[0,0],[0,0]],"v":[[21.042,18.948],[15.272,18.948],[15.272,16.178],[21.042,16.178]],"c":true},"ix":2},"nm":"路径 27","mn":"ADBE Vector Shape - Group","hd":false},{"ind":27,"ty":"sh","ix":28,"ks":{"a":0,"k":{"i":[[-0.67,-1.06],[0,0],[0.86,1],[0,0],[0,0],[0,0]],"o":[[0,0],[-0.53,-0.78],[0,0],[0,0],[0,0],[1.12,1.29]],"v":[[52.34,11.754],[54.36,10.354],[52.27,7.684],[51.67,6.994],[51.67,6.994],[49.68,8.254]],"c":true},"ix":2},"nm":"路径 28","mn":"ADBE Vector Shape - Group","hd":false},{"ind":28,"ty":"sh","ix":29,"ks":{"a":0,"k":{"i":[[-1.06,0],[-0.93,3.19],[0,0],[0,0],[0,0],[0,0],[0,0],[0,0],[0,0],[0,0],[0,0],[0,0],[0,0],[0,0],[0,0],[0,0],[0,0],[0,0],[0,0],[0,0],[0,0],[0,0],[0.01,-0.04],[0,0],[0.12,-0.02],[0.4,1.41],[0,0],[0.02,0.08],[0,0],[0.02,0.09],[0,0],[0,0],[0,0],[0,0],[0.04,0.29],[0,0],[0.05,0.67],[0,0],[0.01,0.18],[0,0],[0.01,0.19],[0,0],[0.01,0.65],[0,0],[0,0],[0,0],[0,1.09],[0,0],[0,0],[0,0],[-0.05,-1.57],[0,0],[0,0],[0,0],[0,0],[0,0],[0,0],[0,0],[0,0],[-0.01,-0.2],[0,0],[-0.17,-1.22],[-0.93,-1.79]],"o":[[1.19,0],[0,0],[0,0],[0,0],[0,0],[0,0],[0,0],[0,0],[0,0],[0,0],[0,0],[0,0],[0,0],[0,0],[0,0],[0,0],[0,0],[0,0],[0,0],[0,0],[0,0],[-0.01,0.05],[0,0],[-0.12,0.31],[-0.46,-0.11],[0,0],[-0.02,-0.08],[0,0],[-0.02,-0.09],[0,0],[0,0],[0,0],[0,0],[-0.03,-0.27],[0,0],[-0.07,-0.6],[0,0],[-0.02,-0.18],[0,0],[-0.01,-0.19],[0,0],[-0.03,-0.61],[0,0],[0,0],[0,0],[-0.04,-1.01],[0,0],[0,0],[0,0],[0,1.65],[0,0],[0,0],[0,0],[0,0],[0,0],[0,0],[0,0],[0,0],[0.01,0.2],[0,0],[0.11,1.5],[0.39,2.86],[0.78,1.49]],"v":[[52.06,32.862],[55.25,28.062],[55.44,27.402],[55.44,27.402],[55.62,26.702],[55.62,26.702],[53.32,24.862],[53.18,25.782],[53.18,25.782],[53.09,26.342],[53.09,26.342],[53,26.862],[53,26.862],[52.91,27.332],[52.91,27.332],[52.82,27.762],[52.82,27.762],[52.73,28.152],[52.73,28.152],[52.65,28.492],[52.65,28.492],[52.56,28.792],[52.52,28.922],[52.43,29.162],[52.06,29.672],[50.78,27.392],[50.66,26.932],[50.6,26.682],[50.48,26.152],[50.42,25.872],[50.3,25.272],[50.3,25.272],[50.18,24.632],[50.18,24.632],[50.07,23.802],[49.97,22.922],[49.79,21.012],[49.71,19.982],[49.67,19.442],[49.6,18.332],[49.57,17.762],[49.52,16.572],[49.46,14.692],[54.64,14.692],[54.64,11.842],[49.4,11.842],[49.35,8.692],[49.34,7.022],[49.34,7.022],[46.49,7.022],[46.54,11.842],[38.06,11.842],[38.06,14.692],[46.63,14.692],[46.65,15.352],[46.65,15.352],[46.7,16.622],[46.7,16.622],[46.77,17.842],[46.8,18.442],[46.88,19.582],[47.3,23.652],[49.29,30.622]],"c":true},"ix":2},"nm":"路径 29","mn":"ADBE Vector Shape - Group","hd":false},{"ind":29,"ty":"sh","ix":30,"ks":{"a":0,"k":{"i":[[-1.04,-1.29],[0,0],[1.68,1.37],[0,0]],"o":[[0,0],[-1.18,-1.35],[0,0],[1.88,1.45]],"v":[[35.57,13.432],[37.56,11.392],[33.27,7.302],[31.2,9.322]],"c":true},"ix":2},"nm":"路径 30","mn":"ADBE Vector Shape - Group","hd":false},{"ind":30,"ty":"sh","ix":31,"ks":{"a":0,"k":{"i":[[0,0],[-1.56,1.68],[0,0],[0,0],[0,0],[0,0],[0.11,-0.13],[0,0],[0,0],[0,0],[0,0],[0,0],[0.51,-0.39]],"o":[[1.77,-1.31],[0,0],[0,0],[0,0],[0,0],[-0.12,0.13],[0,0],[0,0],[0,0],[0,0],[0,0],[0,0.56],[0,0]],"v":[[33.326,32.274],[38.336,27.794],[37.586,24.714],[36.826,25.514],[36.826,25.514],[36.106,26.274],[35.766,26.654],[35.766,15.394],[29.296,15.394],[29.296,18.194],[32.966,18.194],[32.966,28.194],[32.206,29.644]],"c":true},"ix":2},"nm":"路径 31","mn":"ADBE Vector Shape - Group","hd":false},{"ind":31,"ty":"sh","ix":32,"ks":{"a":0,"k":{"i":[[0,0],[-2.43,0.67],[0,0],[1.09,-0.22],[0,0],[0,0],[0,0],[0,0],[0,0],[0,0],[0,0],[0,0]],"o":[[2.74,-0.47],[0,0],[-1.06,0.28],[0,0],[0,0],[0,0],[0,0],[0,0],[0,0],[0,0],[0,0],[0,0]],"v":[[39.294,31.212],[47.074,29.482],[47.074,26.762],[43.854,27.542],[43.854,20.942],[46.184,20.942],[46.184,18.222],[38.704,18.222],[38.704,20.942],[41.004,20.942],[41.004,28.082],[38.564,28.412]],"c":true},"ix":2},"nm":"路径 32","mn":"ADBE Vector Shape - Group","hd":false},{"ind":32,"ty":"sh","ix":33,"ks":{"a":0,"k":{"i":[[-0.67,-1.06],[0,0],[0.86,1],[0,0],[0,0],[0,0]],"o":[[0,0],[-0.53,-0.78],[0,0],[0,0],[0,0],[1.12,1.29]],"v":[[80.84,11.754],[82.86,10.354],[80.77,7.684],[80.17,6.994],[80.17,6.994],[78.18,8.254]],"c":true},"ix":2},"nm":"路径 33","mn":"ADBE Vector Shape - Group","hd":false},{"ind":33,"ty":"sh","ix":34,"ks":{"a":0,"k":{"i":[[-1.06,0],[-0.93,3.19],[0,0],[0,0],[0,0],[0,0],[0,0],[0,0],[0,0],[0,0],[0,0],[0,0],[0,0],[0,0],[0,0],[0,0],[0,0],[0,0],[0,0],[0,0],[0,0],[0,0],[0.01,-0.04],[0,0],[0.12,-0.02],[0.4,1.41],[0,0],[0.02,0.08],[0,0],[0.02,0.09],[0,0],[0,0],[0,0],[0,0],[0.04,0.29],[0,0],[0.05,0.67],[0,0],[0.01,0.18],[0,0],[0.01,0.19],[0,0],[0.01,0.65],[0,0],[0,0],[0,0],[0,1.09],[0,0],[0,0],[0,0],[-0.05,-1.57],[0,0],[0,0],[0,0],[0,0],[0,0],[0,0],[0,0],[0,0],[-0.01,-0.2],[0,0],[-0.05,-0.53],[0,0],[-0.06,-0.45],[-0.93,-1.79]],"o":[[1.19,0],[0,0],[0,0],[0,0],[0,0],[0,0],[0,0],[0,0],[0,0],[0,0],[0,0],[0,0],[0,0],[0,0],[0,0],[0,0],[0,0],[0,0],[0,0],[0,0],[0,0],[-0.01,0.05],[0,0],[-0.12,0.31],[-0.46,-0.11],[0,0],[-0.02,-0.08],[0,0],[-0.02,-0.09],[0,0],[0,0],[0,0],[0,0],[-0.03,-0.27],[0,0],[-0.07,-0.6],[0,0],[-0.02,-0.18],[0,0],[-0.01,-0.19],[0,0],[-0.03,-0.61],[0,0],[0,0],[0,0],[-0.04,-1.01],[0,0],[0,0],[0,0],[0,1.65],[0,0],[0,0],[0,0],[0,0],[0,0],[0,0],[0,0],[0,0],[0.01,0.2],[0,0],[0.04,0.56],[0,0],[0.06,0.5],[0.39,2.86],[0.78,1.49]],"v":[[80.56,32.862],[83.75,28.062],[83.94,27.402],[83.94,27.402],[84.12,26.702],[84.12,26.702],[81.82,24.862],[81.68,25.782],[81.68,25.782],[81.59,26.342],[81.59,26.342],[81.5,26.862],[81.5,26.862],[81.41,27.332],[81.41,27.332],[81.32,27.762],[81.32,27.762],[81.23,28.152],[81.23,28.152],[81.15,28.492],[81.15,28.492],[81.06,28.792],[81.02,28.922],[80.93,29.162],[80.56,29.672],[79.28,27.392],[79.16,26.932],[79.1,26.682],[78.98,26.152],[78.92,25.872],[78.8,25.272],[78.8,25.272],[78.68,24.632],[78.68,24.632],[78.57,23.802],[78.47,22.922],[78.29,21.012],[78.21,19.982],[78.17,19.442],[78.1,18.332],[78.07,17.762],[78.02,16.572],[77.96,14.692],[83.14,14.692],[83.14,11.842],[77.9,11.842],[77.85,8.692],[77.84,7.022],[77.84,7.022],[74.99,7.022],[75.04,11.842],[66.56,11.842],[66.56,14.692],[75.13,14.692],[75.15,15.352],[75.15,15.352],[75.2,16.622],[75.2,16.622],[75.27,17.842],[75.3,18.442],[75.38,19.582],[75.52,21.212],[75.62,22.222],[75.8,23.652],[77.79,30.622]],"c":true},"ix":2},"nm":"路径 34","mn":"ADBE Vector Shape - Group","hd":false},{"ind":34,"ty":"sh","ix":35,"ks":{"a":0,"k":{"i":[[-1.04,-1.29],[0,0],[1.68,1.37],[0,0]],"o":[[0,0],[-1.18,-1.35],[0,0],[1.88,1.45]],"v":[[64.07,13.432],[66.06,11.392],[61.77,7.302],[59.7,9.322]],"c":true},"ix":2},"nm":"路径 35","mn":"ADBE Vector Shape - Group","hd":false},{"ind":35,"ty":"sh","ix":36,"ks":{"a":0,"k":{"i":[[0,0],[-1.56,1.68],[0,0],[0,0],[0,0],[0,0],[0.11,-0.13],[0,0],[0,0],[0,0],[0,0],[0,0],[0.51,-0.39]],"o":[[1.77,-1.31],[0,0],[0,0],[0,0],[0,0],[-0.12,0.13],[0,0],[0,0],[0,0],[0,0],[0,0],[0,0.56],[0,0]],"v":[[61.826,32.274],[66.836,27.794],[66.086,24.714],[65.326,25.514],[65.326,25.514],[64.606,26.274],[64.266,26.654],[64.266,15.394],[57.796,15.394],[57.796,18.194],[61.466,18.194],[61.466,28.194],[60.706,29.644]],"c":true},"ix":2},"nm":"路径 36","mn":"ADBE Vector Shape - Group","hd":false},{"ind":36,"ty":"sh","ix":37,"ks":{"a":0,"k":{"i":[[0,0],[-2.43,0.67],[0,0],[1.09,-0.22],[0,0],[0,0],[0,0],[0,0],[0,0],[0,0],[0,0],[0,0]],"o":[[2.74,-0.47],[0,0],[-1.06,0.28],[0,0],[0,0],[0,0],[0,0],[0,0],[0,0],[0,0],[0,0],[0,0]],"v":[[67.794,31.212],[75.574,29.482],[75.574,26.762],[72.354,27.542],[72.354,20.942],[74.684,20.942],[74.684,18.222],[67.204,18.222],[67.204,20.942],[69.504,20.942],[69.504,28.082],[67.064,28.412]],"c":true},"ix":2},"nm":"路径 37","mn":"ADBE Vector Shape - Group","hd":false},{"ty":"mm","mm":1,"nm":"合并路径 1","mn":"ADBE Vector Filter - Merge","hd":false},{"ty":"fl","c":{"a":0,"k":[1,1,1,1],"ix":4},"o":{"a":0,"k":100,"ix":5},"r":1,"nm":"填充 1","mn":"ADBE Vector Graphic - Fill","hd":false},{"ty":"tr","p":{"a":0,"k":[0,0],"ix":2},"a":{"a":0,"k":[0,0],"ix":1},"s":{"a":0,"k":[150,150],"ix":3},"r":{"a":0,"k":0,"ix":6},"o":{"a":0,"k":100,"ix":7},"sk":{"a":0,"k":0,"ix":4},"sa":{"a":0,"k":0,"ix":5},"nm":"变换"}],"nm":"形状","np":39,"cix":2,"ix":1,"mn":"ADBE Vector Group","hd":false}],"ip":0,"op":300,"st":0,"bm":0},{"ddd":0,"ind":2,"ty":0,"nm":"↻ 手势","refId":"comp_1","sr":1,"ks":{"o":{"a":1,"k":[{"i":{"x":[0.833],"y":[0.833]},"o":{"x":[0.167],"y":[0.167]},"n":["0p833_0p833_0p167_0p167"],"t":0,"s":[0],"e":[100]},{"t":25}],"ix":11},"r":{"a":0,"k":0,"ix":10},"p":{"a":0,"k":[173.461,84,0],"ix":2},"a":{"a":0,"k":[33.5,39.5,0],"ix":1},"s":{"a":1,"k":[{"i":{"x":[0.833,0.833,0.833],"y":[0.833,0.833,0.833]},"o":{"x":[0.167,0.167,0.167],"y":[0.167,0.167,0.167]},"n":["0p833_0p833_0p167_0p167","0p833_0p833_0p167_0p167","0p833_0p833_0p167_0p167"],"t":0,"s":[150,150,100],"e":[94,94,100]},{"i":{"x":[0.833,0.833,0.833],"y":[0.833,0.833,0.833]},"o":{"x":[0.167,0.167,0.167],"y":[0.167,0.167,0.167]},"n":["0p833_0p833_0p167_0p167","0p833_0p833_0p167_0p167","0p833_0p833_0p167_0p167"],"t":16.667,"s":[94,94,100],"e":[100,100,100]},{"i":{"x":[0.833,0.833,0.833],"y":[0.833,0.833,0.833]},"o":{"x":[0.167,0.167,0.167],"y":[0.167,0.167,0.167]},"n":["0p833_0p833_0p167_0p167","0p833_0p833_0p167_0p167","0p833_0p833_0p167_0p167"],"t":25,"s":[100,100,100],"e":[100,100,100]},{"i":{"x":[0.833,0.833,0.833],"y":[0.833,0.833,0.833]},"o":{"x":[0.167,0.167,0.167],"y":[0.167,0.167,0.167]},"n":["0p833_0p833_0p167_0p167","0p833_0p833_0p167_0p167","0p833_0p833_0p167_0p167"],"t":50,"s":[100,100,100],"e":[85,85,100]},{"i":{"x":[0.833,0.833,0.833],"y":[0.833,0.833,0.833]},"o":{"x":[0.167,0.167,0.167],"y":[0.167,0.167,0.167]},"n":["0p833_0p833_0p167_0p167","0p833_0p833_0p167_0p167","0p833_0p833_0p167_0p167"],"t":62.5,"s":[85,85,100],"e":[85,85,100]},{"i":{"x":[0.833,0.833,0.833],"y":[0.833,0.833,0.833]},"o":{"x":[0.167,0.167,0.167],"y":[0.167,0.167,0.167]},"n":["0p833_0p833_0p167_0p167","0p833_0p833_0p167_0p167","0p833_0p833_0p167_0p167"],"t":125,"s":[85,85,100],"e":[100,100,100]},{"t":137.5}],"ix":6}},"ao":0,"w":67,"h":79,"ip":-25,"op":275,"st":-25,"bm":0},{"ddd":0,"ind":3,"ty":4,"nm":"倒计时外环","sr":1,"ks":{"o":{"a":1,"k":[{"i":{"x":[0.833],"y":[0.833]},"o":{"x":[0.167],"y":[0.167]},"n":["0p833_0p833_0p167_0p167"],"t":0,"s":[0],"e":[100]},{"t":25}],"ix":11},"r":{"a":0,"k":0,"ix":10},"p":{"a":0,"k":[168,44.97,0],"ix":2},"a":{"a":0,"k":[0,0,0],"ix":1},"s":{"a":1,"k":[{"i":{"x":[0.833,0.833,0.833],"y":[0.833,0.833,0.833]},"o":{"x":[0.167,0.167,0.167],"y":[0.167,0.167,0.167]},"n":["0p833_0p833_0p167_0p167","0p833_0p833_0p167_0p167","0p833_0p833_0p167_0p167"],"t":0,"s":[150,150,100],"e":[94,94,100]},{"i":{"x":[0.833,0.833,0.833],"y":[0.833,0.833,0.833]},"o":{"x":[0.167,0.167,0.167],"y":[0.167,0.167,0.167]},"n":["0p833_0p833_0p167_0p167","0p833_0p833_0p167_0p167","0p833_0p833_0p167_0p167"],"t":16.667,"s":[94,94,100],"e":[100,100,100]},{"t":25}],"ix":6}},"ao":0,"shapes":[{"ty":"gr","it":[{"ind":0,"ty":"sh","ix":1,"ks":{"a":0,"k":{"i":[[0,0],[0,13.76],[14.36,0],[0,-14.36],[-13.23,-1.21]],"o":[[13.53,-0.91],[0,-14.36],[-14.36,0],[0,13.55],[0,0]],"v":[[1.78,25.97],[26,0.03],[0,-25.97],[-26,0.03],[-2.41,25.92]],"c":false},"ix":2},"nm":"路径 1","mn":"ADBE Vector Shape - Group","hd":false},{"ty":"st","c":{"a":0,"k":[0.972549019608,0.180392156863,0.266666666667,1],"ix":3},"o":{"a":0,"k":100,"ix":4},"w":{"a":0,"k":5,"ix":5},"lc":2,"lj":1,"ml":4,"nm":"描边 1","mn":"ADBE Vector Graphic - Stroke","hd":false},{"ty":"tr","p":{"a":0,"k":[0,0],"ix":2},"a":{"a":0,"k":[0,0],"ix":1},"s":{"a":0,"k":[100,100],"ix":3},"r":{"a":0,"k":0,"ix":6},"o":{"a":0,"k":100,"ix":7},"sk":{"a":0,"k":0,"ix":4},"sa":{"a":0,"k":0,"ix":5},"nm":"变换"}],"nm":"路径","np":2,"cix":2,"ix":1,"mn":"ADBE Vector Group","hd":false},{"ty":"tm","s":{"a":0,"k":0,"ix":1},"e":{"a":1,"k":[{"i":{"x":[0.833],"y":[0.833]},"o":{"x":[0.167],"y":[0.167]},"n":["0p833_0p833_0p167_0p167"],"t":62.5,"s":[100],"e":[0]},{"t":125}],"ix":2},"o":{"a":0,"k":0,"ix":3},"m":1,"ix":2,"nm":"修剪路径 1","mn":"ADBE Vector Filter - Trim","hd":false}],"ip":0,"op":200,"st":-25,"bm":0},{"ddd":0,"ind":4,"ty":4,"nm":"倒计时底","sr":1,"ks":{"o":{"a":1,"k":[{"i":{"x":[0.833],"y":[0.833]},"o":{"x":[0.167],"y":[0.167]},"n":["0p833_0p833_0p167_0p167"],"t":0,"s":[0],"e":[30]},{"t":25}],"ix":11},"r":{"a":0,"k":0,"ix":10},"p":{"a":0,"k":[168,45,0],"ix":2},"a":{"a":0,"k":[0,0,0],"ix":1},"s":{"a":1,"k":[{"i":{"x":[0.833,0.833,0.833],"y":[0.833,0.833,0.833]},"o":{"x":[0.167,0.167,0.167],"y":[0.167,0.167,0.167]},"n":["0p833_0p833_0p167_0p167","0p833_0p833_0p167_0p167","0p833_0p833_0p167_0p167"],"t":0,"s":[150,150,100],"e":[94,94,100]},{"i":{"x":[0.833,0.833,0.833],"y":[0.833,0.833,0.833]},"o":{"x":[0.167,0.167,0.167],"y":[0.167,0.167,0.167]},"n":["0p833_0p833_0p167_0p167","0p833_0p833_0p167_0p167","0p833_0p833_0p167_0p167"],"t":16.667,"s":[94,94,100],"e":[100,100,100]},{"t":25}],"ix":6}},"ao":0,"shapes":[{"ty":"gr","it":[{"d":1,"ty":"el","s":{"a":0,"k":[52,52],"ix":2},"p":{"a":0,"k":[0,0],"ix":3},"nm":"椭圆路径 1","mn":"ADBE Vector Shape - Ellipse","hd":false},{"ty":"st","c":{"a":0,"k":[1,0.219607843137,0.149019607843,1],"ix":3},"o":{"a":0,"k":100,"ix":4},"w":{"a":0,"k":4,"ix":5},"lc":2,"lj":1,"ml":4,"nm":"描边 1","mn":"ADBE Vector Graphic - Stroke","hd":false},{"ty":"gf","o":{"a":0,"k":100,"ix":10},"r":1,"g":{"p":2,"k":{"a":0,"k":[0,1,1,1,1,0,0,0],"ix":9}},"s":{"a":0,"k":[0,26],"ix":5},"e":{"a":0,"k":[0,-23.278],"ix":6},"t":1,"nm":"渐变填充 1","mn":"ADBE Vector Graphic - G-Fill","hd":false},{"ty":"tr","p":{"a":0,"k":[0,0],"ix":2},"a":{"a":0,"k":[0,0],"ix":1},"s":{"a":0,"k":[100,100],"ix":3},"r":{"a":0,"k":0,"ix":6},"o":{"a":0,"k":100,"ix":7},"sk":{"a":0,"k":0,"ix":4},"sa":{"a":0,"k":0,"ix":5},"nm":"变换"}],"nm":"倒计时底","np":3,"cix":2,"ix":1,"mn":"ADBE Vector Group","hd":false}],"ip":0,"op":200,"st":-25,"bm":0}]},{"id":"comp_1","layers":[{"ddd":0,"ind":1,"ty":3,"nm":"▽ 手","sr":1,"ks":{"o":{"a":0,"k":100,"ix":11},"r":{"a":0,"k":0,"ix":10},"p":{"a":0,"k":[33.5,39.5,0],"ix":2},"a":{"a":0,"k":[33.5,39.5,0],"ix":1},"s":{"a":0,"k":[100,100,100],"ix":6}},"ao":0,"ip":0,"op":300,"st":0,"bm":0},{"ddd":0,"ind":2,"ty":4,"nm":"Rectangle","parent":1,"sr":1,"ks":{"o":{"a":0,"k":100,"ix":11},"r":{"a":0,"k":0,"ix":10},"p":{"a":0,"k":[28.5,26,0],"ix":2},"a":{"a":0,"k":[0,0,0],"ix":1},"s":{"a":0,"k":[100,100,100],"ix":6}},"ao":0,"shapes":[{"ty":"gr","it":[{"ty":"rc","d":1,"s":{"a":0,"k":[19,52],"ix":2},"p":{"a":0,"k":[0,0],"ix":3},"r":{"a":0,"k":9.5,"ix":4},"nm":"矩形路径 1","mn":"ADBE Vector Shape - Rect","hd":false},{"ty":"gf","o":{"a":0,"k":100,"ix":10},"r":1,"g":{"p":3,"k":{"a":0,"k":[0,1,1,1,0.5,1,1,1,1,1,1,1,0,1,0.5,0.5,1,0],"ix":9}},"s":{"a":0,"k":[0,-11.454],"ix":5},"e":{"a":0,"k":[0,20.502],"ix":6},"t":1,"nm":"Gradient 02","mn":"ADBE Vector Graphic - G-Fill","hd":false},{"ty":"tr","p":{"a":0,"k":[0,0],"ix":2},"a":{"a":0,"k":[0,0],"ix":1},"s":{"a":0,"k":[100,100],"ix":3},"r":{"a":0,"k":0,"ix":6},"o":{"a":0,"k":100,"ix":7},"sk":{"a":0,"k":0,"ix":4},"sa":{"a":0,"k":0,"ix":5},"nm":"变换"}],"nm":"Gradient 10","np":2,"cix":2,"ix":1,"mn":"ADBE Vector Group","hd":false}],"ip":0,"op":300,"st":0,"bm":0},{"ddd":0,"ind":3,"ty":4,"nm":"Fill 1","parent":1,"sr":1,"ks":{"o":{"a":0,"k":100,"ix":11},"r":{"a":0,"k":0,"ix":10},"p":{"a":0,"k":[33.383,39.4,0],"ix":2},"a":{"a":0,"k":[0,0,0],"ix":1},"s":{"a":0,"k":[-100,100,100],"ix":6}},"ao":0,"shapes":[{"ty":"gr","it":[{"ind":0,"ty":"sh","ix":1,"ks":{"a":0,"k":{"i":[[0,0],[0,0],[0,4.26],[-0.17,0.7],[0,2.92],[-0.35,0.99],[0,0],[0,5.22],[-5.22,0],[0,0],[0,0],[-3.68,3.69],[-3.69,-3.69],[0,0],[-0.22,-0.25],[0,-8.2],[7.27,-5.14],[4.97,-0.33],[0,0],[0,0],[1.31,3.65]],"o":[[0,0],[-3.88,-1.18],[0,-0.76],[-2.08,-1.73],[0,-1.11],[0,0],[-5.22,0],[0,-5.22],[0,0],[0,0],[-3.68,-3.69],[3.7,-3.69],[0,0],[0.24,0.23],[5.57,5.18],[0,9.59],[-3.66,2.93],[0,0],[0,0],[-4.1,0],[0,0]],"v":[[-4.173,26.74],[-4.323,26.3],[-11.023,17.25],[-10.773,15.06],[-14.183,7.8],[-13.643,4.64],[-29.933,4.64],[-39.383,-4.81],[-29.933,-14.26],[5.507,-14.26],[2.897,-16.86],[2.897,-30.23],[16.267,-30.23],[29.637,-16.86],[30.327,-16.13],[39.387,4.64],[27.357,27.83],[14.177,32.95],[14.177,33],[4.727,33],[-4.173,26.74]],"c":false},"ix":2},"nm":"路径 1","mn":"ADBE Vector Shape - Group","hd":false},{"ty":"gf","o":{"a":0,"k":100,"ix":10},"r":1,"g":{"p":3,"k":{"a":0,"k":[0,0.844,0.844,0.844,0.5,0.922,0.922,0.922,1,1,1,1,0,1,0.5,0.65,1,0.301],"ix":9}},"s":{"a":0,"k":[-9.152,-6.59],"ix":5},"e":{"a":0,"k":[39.383,-6.59],"ix":6},"t":1,"nm":"Gradient 03","mn":"ADBE Vector Graphic - G-Fill","hd":false},{"ty":"tr","p":{"a":0,"k":[0,0],"ix":2},"a":{"a":0,"k":[0,0],"ix":1},"s":{"a":0,"k":[100,100],"ix":3},"r":{"a":0,"k":90,"ix":6},"o":{"a":0,"k":100,"ix":7},"sk":{"a":0,"k":0,"ix":4},"sa":{"a":0,"k":0,"ix":5},"nm":"变换"}],"nm":"Fill 1","np":2,"cix":2,"ix":1,"mn":"ADBE Vector Group","hd":false}],"ip":0,"op":300,"st":0,"bm":0}]}],"layers":[{"ddd":0,"ind":1,"ty":0,"nm":"负反馈引导lottie-layout ","refId":"comp_0","sr":1,"ks":{"o":{"a":0,"k":100,"ix":11},"r":{"a":0,"k":0,"ix":10},"p":{"a":0,"k":[87.5,62.5,0],"ix":2},"a":{"a":0,"k":[174,125,0],"ix":1},"s":{"a":0,"k":[52.299,49.8,100],"ix":6}},"ao":0,"w":348,"h":250,"ip":0,"op":200,"st":0,"bm":0}],"markers":[]}